acpp/__init__.py
acpp/__main__.py
acpp/_version.py
acpp/constants.py
acpp/generator.py
acpp/main.py
acpp/templates/classic/doc/images/placeholder-image.png
acpp/templates/classic/docker/Dockerfile
acpp/templates/classic/docker/README.md
acpp/templates/classic/examples/README.md
acpp/templates/classic/src/__init__.py
acpp/templates/classic/src/_version.py
acpp/templates/classic/src/main.py
acpp/templates/classic/tests/Dockerfile
acpp/templates/classic/tests/__init__.py
acpp/templates/classic/tests/conftest.py
acpp/templates/classic/tests/docker-compose.yaml
acpp/templates/classic/tests/test_main.py
acpp/templates/gRPC-api/doc/images/ansys.gif
acpp/templates/gRPC-api/docker/README.md
acpp/templates/gRPC-api/examples/README.md
acpp/templates/gRPC-api/src/__init__.py
acpp/templates/gRPC-api/src/_version.py
acpp/templates/gRPC-api/src/main.py
acpp/templates/gRPC-api/tests/__init__.py
acpp/templates/gRPC-api/tests/conftest.py
acpp/templates/gRPC-api/tests/test_main.py
acpp/templates/package/doc/images/ansys.gif
acpp/templates/package/docker/README.md
acpp/templates/package/examples/README.md
acpp/templates/package/src/__init__.py
acpp/templates/package/src/_version.py
acpp/templates/package/src/main.py
acpp/templates/package/tests/__init__.py
acpp/templates/package/tests/conftest.py
acpp/templates/package/tests/test_main.py
acpp/templates/rest-api/requirements.txt
acpp/templates/rest-api/doc/images/ansys.gif
acpp/templates/rest-api/docker/Dockerfile
acpp/templates/rest-api/docker/README.md
acpp/templates/rest-api/docker/docker-compose.yml
acpp/templates/rest-api/examples/README.md
acpp/templates/rest-api/src/__init__.py
acpp/templates/rest-api/src/_version.py
acpp/templates/rest-api/src/app.py
acpp/templates/rest-api/src/blueprints/__init__.py
acpp/templates/rest-api/src/blueprints/health.py
acpp/templates/rest-api/src/blueprints/version.py
acpp/templates/rest-api/src/models/__init__.py
acpp/templates/rest-api/src/static/swagger.json
ansys_create_python_project-0.0.6.dev0.dist-info/LICENSE
ansys_create_python_project-0.0.6.dev0.dist-info/METADATA
ansys_create_python_project-0.0.6.dev0.dist-info/WHEEL
ansys_create_python_project-0.0.6.dev0.dist-info/top_level.txt
ansys_create_python_project-0.0.6.dev0.dist-info/RECORD
