Metadata-Version: 2.1
Name: ansys-create-python-project
Version: 0.0.6.dev0
Summary: Ansys Python Project Creator
Home-page: 
Author: ANSYS, Inc.
Maintainer: Babacar Fall
Maintainer-email: babacar.fall@ansys.com
License: MIT
Keywords: python,ansys,ace
Platform: UNKNOWN
Classifier: Development Status :: 1 - Planning
Classifier: Intended Audience :: Developers
Classifier: Operating System :: OS Independent
Classifier: Programming Language :: Python :: 3
License-File: LICENSE
Requires-Dist: coloredlogs (~=15.0.1)
Requires-Dist: emoji (~=1.6.3)
